src/__init__.py
src/__version__.py
src/attributes.py
src/cmdline_parser.py
src/css.py
src/fake_data.py
src/indicators.py
src/integrity.py
src/main.py
src/share.py
src/userinfo.py
src/common/__init__.py
src/common/exceptions.py
src/common/utils.py
dhis2_pocket_knife-0.37.1.dist-info/LICENSE.txt
dhis2_pocket_knife-0.37.1.dist-info/METADATA
dhis2_pocket_knife-0.37.1.dist-info/WHEEL
dhis2_pocket_knife-0.37.1.dist-info/entry_points.txt
dhis2_pocket_knife-0.37.1.dist-info/top_level.txt
dhis2_pocket_knife-0.37.1.dist-info/RECORD
