Metadata-Version: 2.1
Name: dhis2-pocket-knife
Version: 0.37.1
Summary: Command-line tools for interacting with DHIS2 REST API
Home-page: https://github.com/davidhuser/dhis2-pk
Author: David Huser
Author-email: dhuser@baosystems.com
License: MIT
Keywords: dhis2
Platform: UNKNOWN
Classifier: License :: OSI Approved :: MIT License
Classifier: Programming Language :: Python
Classifier: Programming Language :: Python :: 3.6
Classifier: Programming Language :: Python :: 3.7
Classifier: Programming Language :: Python :: 3.8
License-File: LICENSE.txt
Requires-Dist: dhis2.py (==2.3.0)
